{
    "ac": "15",
    "languages": "Common, Abyssal",
    "senses": "passive perception 11",
    "scores": [
        {
            "score": 9,
            "stat": "STR",
            "proficient": false
        },
        {
            "score": 16,
            "stat": "DEX",
            "proficient": false
        },
        {
            "score": 12,
            "stat": "CON",
            "proficient": false
        },
        {
            "score": 11,
            "stat": "INT",
            "proficient": false
        },
        {
            "score": 8,
            "stat": "WIS",
            "proficient": false
        },
        {
            "score": 18,
            "stat": "CHA",
            "proficient": false
        }
    ],
    "legendaryActions": [],
    "displayName": "Cultist",
    "hp": "49",
    "legendaryActionCount": 0,
    "type": "Humanoid",
    "speed": "30 ft",
    "skills": [
        {
            "skill": "History",
            "expertise": false,
            "proficient": false
        },
        {
            "skill": "Perception",
            "expertise": false,
            "proficient": true
        },
        {
            "skill": "Performance",
            "expertise": false,
            "proficient": false
        },
        {
            "skill": "Athletics",
            "expertise": false,
            "proficient": false
        },
        {
            "skill": "Persuasion",
            "expertise": false,
            "proficient": false
        },
        {
            "skill": "Intimidation",
            "expertise": false,
            "proficient": false
        },
        {
            "skill": "Insight",
            "expertise": false,
            "proficient": false
        },
        {
            "skill": "Religion",
            "expertise": false,
            "proficient": false
        },
        {
            "skill": "Sleight of Hand",
            "expertise": false,
            "proficient": false
        },
        {
            "skill": "Acrobatics",
            "expertise": false,
            "proficient": false
        },
        {
            "skill": "Arcana",
            "expertise": false,
            "proficient": false
        },
        {
            "skill": "Animal Handling",
            "expertise": false,
            "proficient": false
        },
        {
            "skill": "Deception",
            "expertise": false,
            "proficient": false
        },
        {
            "skill": "Medicine",
            "expertise": false,
            "proficient": false
        },
        {
            "skill": "Stealth",
            "expertise": false,
            "proficient": false
        },
        {
            "skill": "Survival",
            "expertise": false,
            "proficient": false
        },
        {
            "skill": "Nature",
            "expertise": false,
            "proficient": false
        },
        {
            "skill": "Investigation",
            "expertise": false,
            "proficient": false
        }
    ],
    "abilities": [
        {
            "name": "Dark Devotion",
            "description": "The cultist has advantage on saving throws against being charmed or frightened."
        },
        {
            "name": "Spellcasting",
            "description": "The cultist is a 5th-level spellcaster. Their spellcasting ability is Charisma (spell save DC 15, +7 to hit with spell attacks) They know the following spells:\n\nCantrips: Eldritch Blast, Mage Hand, Thaumaturgy\n1st-4th Level (2 4th-level slots): Arms of Hadar, Cause Fear, Command, Ray of Enfeeblement, DIspel Magic, Hypnotic Pattern, Shadow of Moil"
        },
        {
            "name": "Eldritch Upgrade",
            "description": "The cultists adds thier Charisma modifier to the damage dealt by Eldritch Blast. When the cultists hits a creature with Eldrtich Blast, they can pull the creature up to 10 feet closer to them in a straight line. A creature hit by Eldritch Blast gains 1d6 stress"
        }
    ],
    "size": "Medium",
    "name": "Cultist Acolyte (Veteran)",
    "challenge": "5",
    "alignment": "Neutral Evil",
    "actions": [
        {
            "name": "Dagger",
            "description": "Melee Weapon Attack: +6 to hit, reach 5 ft, throw (20/60), one target\nHit: 1d4 + 3 piercing damage"
        },
        {
            "name": "Stressful Incantation (Recharge 4-6)",
            "description": "The cultist targets one creature it can see within 60 ft. If that creature can hear the cultist, it must succeed on a Resolve saving throw against the cultist's spell save DC. On a failed save, the target takes 1d6 psychic damage and gains stress equal to 2d8 + the psychic damage taken. On a successful save, the target takes 1d6 Psychic damage and gains that much stress."
        }
    ]
}