{
    "name": "Stensia - Path to the Mines",
    "theme": "Battle in the Warrens.mp3",
    "lairAction": false,
    "monsterData": [
        {
            "quantity": 2,
            "initiative": 20,
            "xp": 200,
            "reinforcement": true,
            "minion": false,
            "monster": "Quasit"
        },
        {
            "quantity": 2,
            "initiative": 16,
            "xp": 200,
            "reinforcement": true,
            "minion": false,
            "monster": "Quasit"
        },
        {
            "quantity": 1,
            "initiative": 4,
            "xp": 0,
            "reinforcement": false,
            "minion": true,
            "monster": "Commoner"
        }
    ],
    "playerData": [{
        "level": 7,
        "players": 4
    }]
}